advancedworkflow/__init__.py
advancedworkflow/controller.py
advancedworkflow/tests/__init__.py
advancedworkflow/tests/controller.py
TracAdvancedTicketWorkflow-1.2.1.dist-info/COPYING
TracAdvancedTicketWorkflow-1.2.1.dist-info/METADATA
TracAdvancedTicketWorkflow-1.2.1.dist-info/WHEEL
TracAdvancedTicketWorkflow-1.2.1.dist-info/entry_points.txt
TracAdvancedTicketWorkflow-1.2.1.dist-info/top_level.txt
TracAdvancedTicketWorkflow-1.2.1.dist-info/RECORD
